README.md
setup.cfg
setup.py
AztBacktrader/__init__.py
AztBacktrader/azt_broker.py
AztBacktrader/azt_cerebro.py
AztBacktrader/azt_comm_info.py
AztBacktrader/azt_data.py
AztBacktrader/azt_order.py
AztBacktrader/azt_sizer.py
AztBacktrader/azt_store.py
AztBacktrader/azt_strategy.py
AztBacktrader.egg-info/PKG-INFO
AztBacktrader.egg-info/SOURCES.txt
AztBacktrader.egg-info/dependency_links.txt
AztBacktrader.egg-info/requires.txt
AztBacktrader.egg-info/top_level.txt
AztBacktrader/azt_ve_wrapper/__init__.py
AztBacktrader/azt_ve_wrapper/azt_ve_init.py