Metadata-Version: 1.1
Name: AztBacktrader
Version: 0.0.0
Summary: Wrapper From AztQuant Virtual Exchange Python Client To BackTrader
Home-page: https://gitee.com/Qujamlee/azt-backtrader
Author: Qujamlee
Author-email: qujamlee@126.com
License: GNU Lesser General Public License v3.0
Download-URL: https://gitee.com/Qujamlee/azt-backtrader
Keywords: azt,aztve,backtrader,bt
Platform: UNKNOWN
Classifier: Development Status :: 3 - Alpha
Classifier: Intended Audience :: Developers
Classifier: Topic :: Software Development :: Build Tools
Classifier: License :: OSI Approved :: GNU Lesser General Public License v3 or later (LGPLv3+)
Classifier: Programming Language :: Python :: 3.7
Classifier: Programming Language :: Python :: 3.8
Classifier: Programming Language :: Python :: 3.9
Classifier: Programming Language :: Python :: 3.10
